{
  "topics": [
    {
      "id": "variables",
      "title": "Variables & Constants",
      "snippets": [
        {
          "id": "var-declaration",
          "title": "Variable Declaration",
          "code": "var variableName: Type = value",
          "description": "Declare a mutable variable with explicit type"
        },
        {
          "id": "let-declaration",
          "title": "Constant Declaration",
          "code": "let constantName: Type = value",
          "description": "Declare an immutable constant"
        },
        {
          "id": "type-inference",
          "title": "Type Inference",
          "code": "let name = \"Alice\"  // Inferred as String\nlet age = 25        // Inferred as Int\nlet height = 5.9    // Inferred as Double",
          "description": "Let Swift infer types from initial values"
        }
      ]
    },
    {
      "id": "strings",
      "title": "Strings",
      "snippets": [
        {
          "id": "string-interpolation",
          "title": "String Interpolation",
          "code": "let name = \"Alice\"\nlet greeting = \"Hello, \\(name)!\"",
          "description": "Embed values in strings using \\(\\)"
        },
        {
          "id": "multiline-string",
          "title": "Multiline String",
          "code": "let poem = \"\"\"\n    Roses are red,\n    Violets are blue,\n    Swift is awesome,\n    And so are you!\n    \"\"\"",
          "description": "Create multi-line strings with triple quotes"
        },
        {
          "id": "string-methods",
          "title": "Common String Methods",
          "code": "let text = \"  Hello, Swift!  \"\ntext.trimmingCharacters(in: .whitespaces)\ntext.lowercased()\ntext.uppercased()\ntext.hasPrefix(\"Hello\")\ntext.hasSuffix(\"Swift!\")",
          "description": "Essential string manipulation methods"
        }
      ]
    },
    {
      "id": "collections",
      "title": "Collections",
      "snippets": [
        {
          "id": "array-creation",
          "title": "Array Creation",
          "code": "var fruits = [\"Apple\", \"Banana\", \"Orange\"]\nlet emptyInts: [Int] = []\nvar numbers = Array(repeating: 0, count: 5)",
          "description": "Different ways to create arrays"
        },
        {
          "id": "array-access",
          "title": "Array Access",
          "code": "let fruits = [\"Apple\", \"Banana\", \"Orange\"]\nfruits[0]           // \"Apple\"\nfruits.first        // Optional(\"Apple\")\nfruits.last         // Optional(\"Orange\")\nfruits.count        // 3",
          "description": "Access and query array elements"
        },
        {
          "id": "dictionary-creation",
          "title": "Dictionary Creation",
          "code": "var scores = [\"Alice\": 100, \"Bob\": 95]\nlet emptyDict: [String: Int] = [:]\nvar ages: [String: Int] = [:]",
          "description": "Create and initialize dictionaries"
        },
        {
          "id": "set-creation",
          "title": "Set Operations",
          "code": "let colors = Set([\"red\", \"blue\", \"red\", \"green\"])\n// Set is {\"red\", \"blue\", \"green\"}\ncolors.contains(\"blue\")  // true",
          "description": "Create sets and check membership"
        }
      ]
    },
    {
      "id": "control-flow",
      "title": "Control Flow",
      "snippets": [
        {
          "id": "if-statement",
          "title": "If Statement",
          "code": "let temperature = 25\nif temperature > 30 {\n    print(\"It's hot!\")\n} else if temperature > 20 {\n    print(\"Nice weather\")\n} else {\n    print(\"It's cold\")\n}",
          "description": "Basic conditional statement"
        },
        {
          "id": "switch-statement",
          "title": "Switch Statement",
          "code": "let grade = \"A\"\nswitch grade {\ncase \"A\": print(\"Excellent!\")\ncase \"B\": print(\"Good\")\ncase \"C\": print(\"Okay\")\ndefault: print(\"Try harder\")\n}",
          "description": "Match multiple conditions efficiently"
        },
        {
          "id": "for-loop",
          "title": "For Loop",
          "code": "let names = [\"Alice\", \"Bob\", \"Charlie\"]\nfor name in names {\n    print(\"Hello, \\(name)!\")\n}\n\n// With index\nfor (index, name) in names.enumerated() {\n    print(\"\\(index + 1). \\(name)\")\n}",
          "description": "Iterate over collections"
        },
        {
          "id": "while-loop",
          "title": "While Loop",
          "code": "var countdown = 5\nwhile countdown > 0 {\n    print(countdown)\n    countdown -= 1\n}\nprint(\"Liftoff!\")",
          "description": "Loop while condition is true"
        }
      ]
    },
    {
      "id": "functions",
      "title": "Functions",
      "snippets": [
        {
          "id": "basic-function",
          "title": "Basic Function",
          "code": "func greet(name: String) -> String {\n    return \"Hello, \\(name)!\"\n}\n\ngreet(name: \"Alice\")  // \"Hello, Alice!\"",
          "description": "Define a function with parameters and return"
        },
        {
          "id": "default-parameters",
          "title": "Default Parameters",
          "code": "func greet(_ name: String, formal: Bool = false) -> String {\n    if formal {\n        return \"Good day, \\(name).\"\n    }\n    return \"Hey, \\(name)!\"\n}\n\ngreet(\"Alice\")           // \"Hey, Alice!\"\ngreet(\"Bob\", formal: true)  // \"Good day, Bob.\"",
          "description": "Use default values for optional parameters"
        },
        {
          "id": "variadic-parameters",
          "title": "Variadic Parameters",
          "code": "func sum(_ numbers: Int...) -> Int {\n    return numbers.reduce(0, +)\n}\n\nsum(1, 2, 3)    // 6\nsum(4, 5, 6, 7) // 22",
          "description": "Accept variable number of arguments"
        }
      ]
    },
    {
      "id": "optionals",
      "title": "Optionals",
      "snippets": [
        {
          "id": "optional-declaration",
          "title": "Optional Declaration",
          "code": "var name: String? = \"Alice\"\nvar age: Int? = nil\n\n// Check before use\nif let actualName = name {\n    print(\"Name is \\(actualName)\")\n}",
          "description": "Declare optional values that may be nil"
        },
        {
          "id": "nil-coalescing",
          "title": "Nil Coalescing",
          "code": "let optionalName: String? = nil\nlet defaultName = optionalName ?? \"Anonymous\"\n// defaultName is \"Anonymous\"",
          "description": "Provide default value when optional is nil"
        },
        {
          "id": "optional-chaining",
          "title": "Optional Chaining",
          "code": "struct Person {\n    var address: Address?\n}\n\nstruct Address {\n    var city: String\n}\n\nlet person = Person()\nlet city = person.address?.city ?? \"Unknown\"",
          "description": "Safely access nested optional properties"
        }
      ]
    },
    {
      "id": "swiftui",
      "title": "SwiftUI",
      "snippets": [
        {
          "id": "basic-view",
          "title": "Basic View",
          "code": "import SwiftUI\n\nstruct ContentView: View {\n    var body: some View {\n        Text(\"Hello, SwiftUI!\")\n    }\n}",
          "description": "Create a simple SwiftUI view"
        },
        {
          "id": "vstack-hstack",
          "title": "VStack & HStack",
          "code": "VStack(alignment: .leading, spacing: 20) {\n    HStack {\n        Image(systemName: \"star.fill\")\n        Text(\"Favorite\")\n    }\n    Text(\"More content here\")\n}",
          "description": "Combine VStack and HStack for layouts"
        },
        {
          "id": "state-property",
          "title": "@State Property",
          "code": "struct CounterView: View {\n    @State private var count = 0\n    \n    var body: some View {\n        VStack {\n            Text(\"Count: \\(count)\")\n            Button(\"Increment\") {\n                count += 1\n            }\n        }\n    }\n}",
          "description": "Use @State for local view state"
        }
      ]
    }
  ]
}